{"status": [{"hidden": true, "_id": "54d0299cbb29d9802e01d49f", "name": "Temp"}, {"hidden": false, "_id": "54d0299cbb29d9802e01d49e", "name": "Ignore"}, {"hidden": true, "_id": "54d0299cbb29d9802e01d49d", "name": "Deleted"}, {"hidden": true, "_id": "54d0299cbb29d9802e01d49c", "name": "Unknown"}, {"hidden": true, "_id": "54d0299cbb29d9802e01d49b", "name": "Post Processing Fail"}, {"hidden": true, "_id": "54d0299cbb29d9802e01d49a", "name": "Failed"}, {"hidden": true, "_id": "54d0299cbb29d9802e01d499", "name": "Completed"}, {"hidden": false, "_id": "54d0299cbb29d9802e01d498", "name": "Downloaded"}, {"hidden": false, "_id": "54d0299cbb29d9802e01d497", "name": "Snatched"}, {"hidden": false, "_id": "54d0299cbb29d9802e01d496", "name": "Wanted"}, {"hidden": true, "_id": "54d0299cbb29d9802e01d4a0", "name": "Downloading"}], "repo": [{"url": "https://raw.github.com/lad1337/XDM-main-plugin-repo/master/meta.json", "_id": "54d0299cbb29d9802e01d4a1", "name": "XDM demo", "info_url": "https://github.com/lad1337/XDM-main-plugin-repo/"}], "status.read_preference": [], "repo.read_preference": []}